{
  "resource": "Customer App: Room Details",
  "resource_explanation": null,
  "http_method": "GET",
  "route": "/api/v1/rooms/:id",
  "description": "gets the details of a room",
  "explanation": null,
  "parameters": [

  ],
  "response_fields": [

  ],
  "requests": [
    {
      "request_method": "GET",
      "request_path": "/api/v1/rooms/125?hotel_id=126",
      "request_body": null,
      "request_headers": {
        "Content-Type": "application/json",
        "Authorization": "eyJhbGciOiJIUzI1NiJ9.eyJjdXN0b21lcl9pZCI6MjE4LCJwYXNzd29yZCI6InBhc3N3b3JkIiwiZXhwIjoxNjE5MTQyMTMzfQ.p3sLZ_g_dir90G55Q7lHKHTWmjxB9tOGBDcbSYHOEq4",
        "Host": "example.org",
        "Cookie": ""
      },
      "request_query_parameters": {
        "hotel_id": "126"
      },
      "request_content_type": "application/json",
      "response_status": 200,
      "response_status_text": "OK",
      "response_body": "{\n  \"data\": {\n    \"id\": \"125\",\n    \"type\": \"room\",\n    \"attributes\": {\n      \"name\": \"Room101\",\n      \"description\": \"guest room,  awesome room\",\n      \"room_type\": \"single\",\n      \"room_class\": \"standard\",\n      \"total_quantity\": 1\n    },\n    \"relationships\": {\n      \"amenities\": {\n        \"data\": [\n          {\n            \"id\": \"140\",\n            \"type\": \"amenity\"\n          }\n        ]\n      },\n      \"room_rates\": {\n        \"data\": [\n          {\n            \"id\": \"140\",\n            \"type\": \"room_rate\"\n          }\n        ]\n      }\n    }\n  },\n  \"included\": [\n    {\n      \"id\": \"140\",\n      \"type\": \"amenity\",\n      \"attributes\": {\n        \"name\": \"Towel\",\n        \"description\": \"Towel to wipe your\",\n        \"is_available\": true\n      }\n    },\n    {\n      \"id\": \"140\",\n      \"type\": \"room_rate\",\n      \"attributes\": {\n        \"rate_type\": \"standard\",\n        \"min_price\": 10000.0,\n        \"max_price\": 1000.0,\n        \"is_active\": true\n      }\n    }\n  ]\n}",
      "response_headers": {
        "X-Frame-Options": "SAMEORIGIN",
        "X-XSS-Protection": "1; mode=block",
        "X-Content-Type-Options": "nosniff",
        "X-Download-Options": "noopen",
        "X-Permitted-Cross-Domain-Policies": "none",
        "Referrer-Policy": "strict-origin-when-cross-origin",
        "Content-Type": "application/vnd.api+json; charset=utf-8",
        "ETag": "W/\"0dd7491638d8599d5454cf1f1ef0e9bd\"",
        "Cache-Control": "max-age=0, private, must-revalidate",
        "X-Request-Id": "89bb4e57-c9f4-496d-8148-f8093ac29b86",
        "X-Runtime": "0.007826",
        "Vary": "Origin",
        "Content-Length": "554"
      },
      "response_content_type": "application/vnd.api+json; charset=utf-8",
      "curl": null
    }
  ]
}